scraper/__init__.py
scraper/scraper.py
sescraper-0.2.0.dist-info/LICENSE
sescraper-0.2.0.dist-info/METADATA
sescraper-0.2.0.dist-info/WHEEL
sescraper-0.2.0.dist-info/top_level.txt
sescraper-0.2.0.dist-info/RECORD
